smart_spread/__init__.py
smart_spread/smart_spread.py
smart_spread/smart_tab.py
smartspread-1.0.7.dist-info/METADATA
smartspread-1.0.7.dist-info/WHEEL
smartspread-1.0.7.dist-info/top_level.txt
smartspread-1.0.7.dist-info/RECORD
