Metadata-Version: 2.4
Name: smartspread
Version: 1.0.7
Summary: A Python library that extends gspread for enhanced spreadsheet manipulation.
Author-email: Arved Klöhn <arved.kloehn@gmail.com>
Project-URL: Homepage, https://github.com/Redundando/smart_spread
Project-URL: Repository, https://github.com/Redundando/smart_spread
Project-URL: Issues, https://github.com/Redundando/smart_spread/issues
Project-URL: Documentation, https://github.com/Redundando/smart_spread#readme
Keywords: google-sheets,gspread,pandas,spreadsheet,automation
Requires-Python: >=3.7
Requires-Dist: gspread>=5.0.0
Requires-Dist: pandas>=1.3.0
Requires-Dist: cacherator>=0.1.0
Requires-Dist: logorator>=0.1.0
